lexee/Iterator.py
lexee/LexeeDoc.py
lexee/__init__.py
lexee/__main__.py
lexee/config.py
lexee/data.py
lexee/expression.py
lexee/generator.py
lexee/import.py
lexee/interfaces.py
lexee/interpreter.py
lexee/symbol.py
lexee/variable.py
lexee/writer.py
lexee/expressions/__init__.py
lexee/expressions/variable.py
lexee/symbols/__init__.py
lexee/symbols/config.py
lexee/symbols/data.py
lexee/symbols/generator.py
lexee/symbols/import.py
lexee/symbols/variable.py
lexee-0.0.9.dist-info/LICENSE
lexee-0.0.9.dist-info/METADATA
lexee-0.0.9.dist-info/WHEEL
lexee-0.0.9.dist-info/top_level.txt
lexee-0.0.9.dist-info/RECORD
