Metadata-Version: 2.1
Name: lexee
Version: 0.0.9
Summary: Pylingo interpreter
Home-page: https://github.com/dialectsoftware/lexee
Author: Dialect Software LLC
Author-email: support@dialectsoftware.com
License: UNKNOWN
Platform: UNKNOWN
Classifier: Programming Language :: Python :: 3.6
Classifier: License :: OSI Approved :: MIT License
Classifier: Operating System :: OS Independent
Requires-Dist: Pykka
Requires-Dist: jinja2
Requires-Dist: PyYAML
Requires-Dist: Protolingo
Requires-Dist: Pylingo
